{
"type": "FeatureCollection",
"name": "transit_stops",
"crs": { "type": "name", "properties": { "name": "urn:ogc:def:crs:OGC:1.3:CRS84" } },
"features": [
{ "type": "Feature", "properties": { "mode": "R" }, "geometry": { "type": "Point", "coordinates": [ -79.866117308939479, 43.266637008994941 ] } },
{ "type": "Feature", "properties": { "mode": "R" }, "geometry": { "type": "Point", "coordinates": [ -79.869186559356024, 43.253104576253882 ] } }
]
}
